[
{"dailysummary":"{\"date\":{\"pretty\":\"12:00 PM EST on April 05, 2012\",\"min\":\"00\",\"hour\":\"12\",\"year\":\"2012\",\"mday\":\"05\",\"mon\":\"04\",\"tzname\":\"America\\\/New_York\"},\"snowfallm\":\"0.00\",\"maxtempm\":\"14\",\"minwspdi\":\"0\",\"precipi\":\"0.27\",\"snowfalli\":\"0.00\",\"maxtempi\":\"57\",\"precipm\":\"30.86\",\"meanpressurem\":\"1012\",\"meantempm\":\"22\",\"thunder\":\"0\",\"meantempi\":\"52\",\"minwspdm\":\"0\",\"meanvisi\":\"10\",\"maxwspdi\":\"21\",\"meanvism\":\"15\",\"mintempm\":\"9\",\"minhumidity\":\"59\",\"mintempi\":\"48\",\"maxwspdm\":\"34\",\"rain\":\"0\",\"gdegreedays\":\"2\",\"minpressurem\":\"1005\",\"minvisi\":\"8\",\"tornado\":\"0\",\"meandewpti\":\"44\",\"maxhumidity\":\"93\",\"minpressurei\":\"29.67\",\"minvism\":\"13\",\"meandewptm\":\"7\",\"maxpressurem\":\"1020\",\"hail\":\"0\",\"meanwindspdm\":\"11\",\"maxpressurei\":\"30.12\",\"meanwdird\":\"255\",\"maxvism\":\"16\",\"meanwindspdi\":\"7\",\"mindewptm\":\"6\",\"maxvisi\":\"10\",\"meanpressurei\":\"29.88\",\"snow\":\"1\",\"mindewpti\":\"42\",\"heatingdegreedays\":\"12\",\"maxdewptm\":\"8\",\"coolingdegreedays\":\"0\",\"fog\":\"0\",\"maxdewpti\":\"46\"}"}
]